Metadata-Version: 2.1
Name: python-aka
Version: 0.0.9
Summary: Interact with AKA through Python
Home-page: UNKNOWN
Author: Drew Stinnett
Author-email: drew.stinnett@duke.edu
License: BSD
Keywords: aka cli
Platform: UNKNOWN
